LocalSearch/__init__.py
LocalSearch/backend/__init__.py
LocalSearch/backend/engine.py
LocalSearch/backend/main.py
LocalSearch/backend/_doc_loader/__init__.py
LocalSearch/backend/_doc_loader/_embedding_processor.py
LocalSearch/backend/_doc_loader/_scan.py
LocalSearch/backend/_search/__init__.py
LocalSearch/backend/_search/_search.py
LocalSearch/backend/embeddings/BaseEmbeddings.py
LocalSearch/backend/embeddings/SentenceTransformerEmbedder.py
LocalSearch/backend/embeddings/__init__.py
LocalSearch/backend/llms/BaseLLM.py
LocalSearch/backend/llms/GroqLLM.py
LocalSearch/backend/llms/__init__.py
LocalSearch/backend/metadata_store/BaseMetaDataStore.py
LocalSearch/backend/metadata_store/JsonMetadataStore.py
LocalSearch/backend/metadata_store/__init__.py
LocalSearch/backend/text_extractor/BaseTextExtractor.py
LocalSearch/backend/text_extractor/DefaultTextExtractor.py
LocalSearch/backend/text_extractor/__init__.py
LocalSearch/backend/vector_store/BaseVectorStore.py
LocalSearch/backend/vector_store/FaissVectorStore.py
LocalSearch/backend/vector_store/__init__.py
docs/conf.py
localsearch-0.0.1.dist-info/licenses/License
localsearch-0.0.1.dist-info/METADATA
localsearch-0.0.1.dist-info/WHEEL
localsearch-0.0.1.dist-info/top_level.txt
localsearch-0.0.1.dist-info/RECORD
