Metadata-Version: 2.4
Name: LocalSearch
Version: 0.0.1
Summary: Local AI search engine for folders with a web interface
Author: Rick Sanchez
License: MIT
Requires-Python: >=3.10
License-File: License
Requires-Dist: beautifulsoup4==4.14.2
Requires-Dist: faiss-cpu==1.9.0
Requires-Dist: fastapi==0.120.0
Requires-Dist: pymupdf
Requires-Dist: groq==0.33.0
Requires-Dist: numpy
Requires-Dist: pydantic==2.12.3
Requires-Dist: sentence_transformers==4.1.0
Requires-Dist: starlette==0.48.0
Requires-Dist: uvicorn==0.38.0
Dynamic: license-file
